{
    "invoice_number": {
        "value": "F1000876/23",
        "confidence": 0.966
    },
    "vendor_name": {
        "value": "COMPANY",
        "confidence": 0.391
    },
    "invoice_date": {
        "value": "2023-08-14",
        "confidence": 0.966
    },
    "total_amount": {
        "value": 62232.3,
        "confidence": 0.95
    },
    "purchase_order": {
        "value": "X001525",
        "confidence": 0.535
    },
    "due_date": {
        "value": "nil",
        "confidence": 0.0
    },
    "gst_number": {
        "value": "nil",
        "confidence": 0.0
    },
    "tax_amount": {
        "value": 10372.05,
        "confidence": 0.957
    }
}